inspire_interact/__init__.py
inspire_interact/api.py
inspire_interact/clean_up.py
inspire_interact/constants.py
inspire_interact/handle_results.py
inspire_interact/html_snippets.py
inspire_interact/inspire_execute.py
inspire_interact/inspire_script.py
inspire_interact/queue_manager.py
inspire_interact/utils.py
inspire_interact/static/aboutus.jpeg
inspire_interact/static/favicon.ico
inspire_interact/static/help.png
inspire_interact/static/inSPIRE-logo-nobg.png
inspire_interact/static/inSPIRE-logo.png
inspire_interact/static/index.js
inspire_interact/static/plot_1.png
inspire_interact/static/styles/style.css
inspire_interact/templates/404.html
inspire_interact/templates/about.html
inspire_interact/templates/contact.html
inspire_interact/templates/delete.html
inspire_interact/templates/download.html
inspire_interact/templates/failed.html
inspire_interact/templates/faq.html
inspire_interact/templates/home.html
inspire_interact/templates/index.html
inspire_interact/templates/ms.html
inspire_interact/templates/parameters.html
inspire_interact/templates/proteome-pathogen.html
inspire_interact/templates/proteome-standard.html
inspire_interact/templates/queued.html
inspire_interact/templates/ready.html
inspire_interact/templates/references.html
inspire_interact/templates/search.html
inspire_interact/templates/usecase.html
inspire_interact/templates/view-queue.html
inspire_interact/templates/waiting.html
inspire_interact-0.6.dist-info/LICENSE
inspire_interact-0.6.dist-info/METADATA
inspire_interact-0.6.dist-info/WHEEL
inspire_interact-0.6.dist-info/entry_points.txt
inspire_interact-0.6.dist-info/top_level.txt
inspire_interact-0.6.dist-info/RECORD
