Metadata-Version: 2.1
Name: inspire-interact
Version: 0.6
Summary: Interactive GUI for inSPIRE Platform.
Author: John Cormican, Sahil Khan, Juliane Liepe, Manuel S. Pereira
Author-email: juliane.liepe@mpinat.mpg.de
Project-URL: Homepage, https://github.com/QuantSysBio/inSPIRE-interactive
Project-URL: Tracker, https://github.com/QuantSysBio/inSPIRE-interactive/issues
Requires-Python: >=3.11
License-File: LICENSE
Requires-Dist: inspirems ==2.0rc7
Requires-Dist: blinker ==1.6.2
Requires-Dist: click ==8.1.3
Requires-Dist: flask ==2.3.2
Requires-Dist: flask-cors ==3.0.10
Requires-Dist: itsdangerous ==2.1.2
Requires-Dist: psutil ==5.9.6
Requires-Dist: Werkzeug ==3.0.1
